fibonacci_calculator/cli.py
fibonacci_calculator/fibonacci_calculator.c
fibonacci_calculator/fibonacci_calculator.cpython-38-x86_64-linux-gnu.so
fibonacci_calculator/fibonacci_calculator.py
fibonacci_calculator/__init__.py
fibonacci_calculator/pure_python/fibonacci_calculator_pure.py
fibonacci_calculator/pure_python/cli.py
fibonacci_calculator/pure_python/__init__.py
fibonacci_calculator-0.1.28.dist-info/METADATA
fibonacci_calculator-0.1.28.dist-info/WHEEL
fibonacci_calculator-0.1.28.dist-info/top_level.txt
fibonacci_calculator-0.1.28.dist-info/entry_points.txt
fibonacci_calculator-0.1.28.dist-info/RECORD
