Metadata-Version: 2.1
Name: fibonacci-calculator
Version: 0.1.28
Summary: Fibonacci Calculator including normal Python code and Cython wrapper.
Home-page: https://github.com/richardscholtens/Fibonacci_Calculator
Author: Richard Scholtens
Author-email: richardscholtens2@gmail.com
License: MIT license
Keywords: fibonacci_calculator
Platform: UNKNOWN
Classifier: Development Status :: 2 - Pre-Alpha
Classifier: Intended Audience :: Developers
Classifier: License :: OSI Approved :: MIT License
Classifier: Natural Language :: English
Classifier: Programming Language :: Python :: 3
Classifier: Programming Language :: Python :: 3.6
Classifier: Programming Language :: Python :: 3.7
Classifier: Programming Language :: Python :: 3.8
Requires-Python: >=3.6
Requires-Dist: Click (>=7.0)
Requires-Dist: Cython (>=0.29.21)
Requires-Dist: numpy (==1.19.2)
